llm_instrumentation/__init__.py
llm_instrumentation/py.typed
llm_instrumentation/analysis/__init__.py
llm_instrumentation/analysis/causal_graph.py
llm_instrumentation/analysis/sparse_autoencoder.py
llm_instrumentation/analysis/visualization.py
llm_instrumentation/cli/__init__.py
llm_instrumentation/cli/llm_prof.py
llm_instrumentation/core/__init__.py
llm_instrumentation/core/auto_detect.py
llm_instrumentation/core/checkpoint.py
llm_instrumentation/core/compression.py
llm_instrumentation/core/config.py
llm_instrumentation/core/framework.py
llm_instrumentation/core/hooks.py
llm_instrumentation/core/profiling.py
llm_instrumentation/core/streaming.py
llm_instrumentation/ebpf/__init__.py
llm_instrumentation/ebpf/bpf_loader.py
llm_instrumentation/ebpf/exceptions.py
llm_instrumentation/ebpf/aggregator/__init__.py
llm_instrumentation/ebpf/aggregator/interval.py
llm_instrumentation/ebpf/collectors/__init__.py
llm_instrumentation/ebpf/collectors/base.py
llm_instrumentation/ebpf/collectors/disk_io.py
llm_instrumentation/ebpf/collectors/mem.py
llm_instrumentation/ebpf/collectors/net.py
llm_instrumentation/ebpf/collectors/sched.py
llm_instrumentation/ebpf/collectors/sync_wait.py
llm_instrumentation/ebpf/collectors/syscalls_io.py
llm_instrumentation/ebpf/correlation/__init__.py
llm_instrumentation/ebpf/correlation/context.py
llm_instrumentation/memory/__init__.py
llm_instrumentation/memory/async_writer.py
llm_instrumentation/memory/cuda_manager.py
llm_instrumentation/memory/ring_buffer.py
llm_instrumentation/utils/__init__.py
llm_instrumentation/utils/config.py
llm_instrumentation/utils/logging.py
llm_instrumentation/utils/metrics.py
llm_instrumentation-1.3.1.data/scripts/tracepoints.py
llm_instrumentation-1.3.1.dist-info/METADATA
llm_instrumentation-1.3.1.dist-info/WHEEL
llm_instrumentation-1.3.1.dist-info/entry_points.txt
llm_instrumentation-1.3.1.dist-info/top_level.txt
llm_instrumentation-1.3.1.dist-info/RECORD
