Metadata-Version: 2.4
Name: llm-instrumentation
Version: 1.3.1
Summary: A high-performance instrumentation framework for capturing, streaming, and analyzing internal activations of large language models
Author-email: Ruben Fernandez Boullon <rubenfernandezboullon@gmail.com>
Project-URL: Homepage, https://github.com/rubenfb23/STRAP-LLM
Project-URL: Repository, https://github.com/rubenfb23/STRAP-LLM
Project-URL: Bug Tracker, https://github.com/rubenfb23/STRAP-LLM/issues
Project-URL: Documentation, https://github.com/rubenfb23/STRAP-LLM/tree/main/llm-instrumentation/docs
Keywords: llm,instrumentation,interpretability,pytorch,transformers,profiling
Classifier: Development Status :: 3 - Alpha
Classifier: Intended Audience :: Developers
Classifier: Intended Audience :: Science/Research
Classifier: License :: OSI Approved :: MIT License
Classifier: Operating System :: POSIX :: Linux
Classifier: Programming Language :: Python :: 3
Classifier: Programming Language :: Python :: 3.8
Classifier: Programming Language :: Python :: 3.9
Classifier: Programming Language :: Python :: 3.10
Classifier: Programming Language :: Python :: 3.11
Classifier: Programming Language :: Python :: 3.12
Classifier: Topic :: Scientific/Engineering :: Artificial Intelligence
Classifier: Topic :: System :: Monitoring
Requires-Python: >=3.8
Requires-Dist: torch>=2.0.0
Requires-Dist: numpy>=1.24.0
Requires-Dist: lz4>=4.0.0
Requires-Dist: zstandard>=0.20.0
Requires-Dist: aiofiles>=23.0.0
Provides-Extra: dev
Requires-Dist: pytest>=7.0.0; extra == "dev"
Requires-Dist: pytest-asyncio>=0.21.0; extra == "dev"
Requires-Dist: black>=23.0.0; extra == "dev"
Requires-Dist: flake8>=6.0.0; extra == "dev"
Requires-Dist: mypy>=1.0.0; extra == "dev"
Provides-Extra: ebpf
Requires-Dist: bcc>=0.1.0; extra == "ebpf"
Provides-Extra: analysis
Requires-Dist: matplotlib>=3.5.0; extra == "analysis"
Requires-Dist: networkx>=3.0; extra == "analysis"
Requires-Dist: pandas>=1.5.0; extra == "analysis"
Provides-Extra: notebooks
Requires-Dist: jupyter>=1.0.0; extra == "notebooks"
Requires-Dist: ipython>=8.0.0; extra == "notebooks"
Provides-Extra: huggingface
Requires-Dist: transformers>=4.30.0; extra == "huggingface"
Provides-Extra: monitoring
Requires-Dist: psutil>=5.9.0; extra == "monitoring"
Provides-Extra: all
Requires-Dist: pytest>=7.0.0; extra == "all"
Requires-Dist: pytest-asyncio>=0.21.0; extra == "all"
Requires-Dist: black>=23.0.0; extra == "all"
Requires-Dist: flake8>=6.0.0; extra == "all"
Requires-Dist: mypy>=1.0.0; extra == "all"
Requires-Dist: bcc>=0.1.0; extra == "all"
Requires-Dist: matplotlib>=3.5.0; extra == "all"
Requires-Dist: networkx>=3.0; extra == "all"
Requires-Dist: jupyter>=1.0.0; extra == "all"
Requires-Dist: ipython>=8.0.0; extra == "all"
Requires-Dist: transformers>=4.30.0; extra == "all"
Requires-Dist: psutil>=5.9.0; extra == "all"
